poetry/__init__.py
poetry/core/__init__.py
poetry/core/_vendor/_pyrsistent_version.py
poetry/core/_vendor/attr/__init__.py
poetry/core/_vendor/attr/_compat.py
poetry/core/_vendor/attr/_config.py
poetry/core/_vendor/attr/_funcs.py
poetry/core/_vendor/attr/_make.py
poetry/core/_vendor/attr/_next_gen.py
poetry/core/_vendor/attr/_version_info.py
poetry/core/_vendor/attr/converters.py
poetry/core/_vendor/attr/exceptions.py
poetry/core/_vendor/attr/filters.py
poetry/core/_vendor/attr/py.typed
poetry/core/_vendor/attr/setters.py
poetry/core/_vendor/attr/validators.py
poetry/core/_vendor/attrs.LICENSE
poetry/core/_vendor/jsonschema/COPYING
poetry/core/_vendor/jsonschema/LICENSE
poetry/core/_vendor/jsonschema/__init__.py
poetry/core/_vendor/jsonschema/__main__.py
poetry/core/_vendor/jsonschema/_format.py
poetry/core/_vendor/jsonschema/_legacy_validators.py
poetry/core/_vendor/jsonschema/_reflect.py
poetry/core/_vendor/jsonschema/_types.py
poetry/core/_vendor/jsonschema/_utils.py
poetry/core/_vendor/jsonschema/_validators.py
poetry/core/_vendor/jsonschema/benchmarks/__init__.py
poetry/core/_vendor/jsonschema/benchmarks/issue232.py
poetry/core/_vendor/jsonschema/benchmarks/json_schema_test_suite.py
poetry/core/_vendor/jsonschema/cli.py
poetry/core/_vendor/jsonschema/compat.py
poetry/core/_vendor/jsonschema/exceptions.py
poetry/core/_vendor/jsonschema/schemas/draft3.json
poetry/core/_vendor/jsonschema/schemas/draft4.json
poetry/core/_vendor/jsonschema/schemas/draft6.json
poetry/core/_vendor/jsonschema/schemas/draft7.json
poetry/core/_vendor/jsonschema/validators.py
poetry/core/_vendor/lark/__init__.py
poetry/core/_vendor/lark/__pyinstaller/__init__.py
poetry/core/_vendor/lark/__pyinstaller/hook-lark.py
poetry/core/_vendor/lark/common.py
poetry/core/_vendor/lark/exceptions.py
poetry/core/_vendor/lark/grammar.py
poetry/core/_vendor/lark/grammars/common.lark
poetry/core/_vendor/lark/indenter.py
poetry/core/_vendor/lark/lark.py
poetry/core/_vendor/lark/lexer.py
relaxed_poetry_core-0.4.1.dist-info/LICENSE
relaxed_poetry_core-0.4.1.dist-info/WHEEL
relaxed_poetry_core-0.4.1.dist-info/METADATA
relaxed_poetry_core-0.4.1.dist-info/RECORD
