Metadata-Version: 2.1
Name: relaxed-poetry-core
Version: 0.4.1
Summary: Fork of poetry-core, with some relaxations
Home-page: https://github.com/bennylut/relaxed-poetry-core
License: MIT
Keywords: packaging,dependency,poetry,relaxed-poetry
Author: bennylut
Requires-Python: >=3.6,<4.0
Classifier: License :: OSI Approved :: MIT License
Classifier: Programming Language :: Python :: 3
Classifier: Programming Language :: Python :: 3.6
Classifier: Programming Language :: Python :: 3.7
Classifier: Programming Language :: Python :: 3.8
Classifier: Programming Language :: Python :: 3.9
Classifier: Programming Language :: Python :: 3.10
Classifier: Topic :: Software Development :: Build Tools
Classifier: Topic :: Software Development :: Libraries :: Python Modules
Requires-Dist: dataclasses (>=0.8); python_version >= "3.6" and python_version < "3.7"
Requires-Dist: importlib-metadata (>=1.7.0); python_version < "3.8"
Project-URL: Bug Tracker, https://github.com/bennylut/relaxed-poetry/issues
Project-URL: Repository, https://github.com/bennylut/relaxed-poetry-core
